{
  "apts": [
    {
      "lat": 36.177226,
      "lng": -86.784655,
      "rentSummary": "$1,395+/mo",
      "name": "LC Germantown"
    },
    {
      "lat": 36.148450,
      "lng": -86.798000,
      "rentSummary": "$1,646+/mo",
      "name": "Residences at Aertson Midtown"
    },
    {
      "lat": 36.190146,
      "lng": -86.795210,
      "rentSummary": "$1,285+/mo",
      "name": "One Metrocenter"
    },
    {
      "lat": 36.140830,
      "lng": -86.793207,
      "rentSummary": "$1,175+/mo",
      "name": "Note 16"
    },
    {
      "lat": 36.151099,
      "lng": -86.787430,
      "rentSummary": "$1,225+/mo",
      "name": "Novel Music Row"
    },
    {
      "lat": 36.153571,
      "lng": -86.794440,
      "rentSummary": "$1,610+/mo",
      "name": "SkyHouse Nashville"
    },
    {
      "lat": 36.153007,
      "lng": -86.782194,
      "rentSummary": "$1,163+/mo",
      "name": "Velocity in the Gulch"
    },
    {
      "lat": 36.159709,
      "lng": -86.773955,
      "rentSummary": "$1,320+/mo",
      "name": "The SoBro"
    },
    {
      "lat": 36.142035,
      "lng": -86.820110,
      "rentSummary": "$1,248+/mo",
      "name": "Acklen West End"
    },
    {
      "lat": 36.173837,
      "lng": -86.787716,
      "rentSummary": "$1,285+/mo",
      "name": "Carillon"
    },
    {
      "lat": 36.127273,
      "lng": -86.777261,
      "rentSummary": "$1,330+/mo",
      "name": "Octave"
    },
    {
      "lat": 36.145841,
      "lng": -86.817450,
      "rentSummary": "$1,277+/mo",
      "name": "West End Village"
    },
    {
      "lat": 36.148873,
      "lng": -86.809195,
      "rentSummary": "$1,530+/mo",
      "name": "ParkCentral"
    },
    {
      "lat": 36.151800,
      "lng": -86.820500,
      "rentSummary": "$1,475+/mo",
      "name": "The Shay"
    },
    {
      "lat": 36.158103,
      "lng": -86.789557,
      "rentSummary": "$1,317+/mo",
      "name": "The Gossett on Church"
    },
    {
      "lat": 36.159018,
      "lng": -86.787768,
      "rentSummary": "$1,382+/mo",
      "name": "Eleven North"
    },
    {
      "lat": 36.152122,
      "lng": -86.790467,
      "rentSummary": "$1,490+/mo",
      "name": "Element Music Row"
    },
    {
      "lat": 36.154871,
      "lng": -86.775272,
      "rentSummary": "$1,219+/mo",
      "name": "Olmsted Nashville"
    },
    {
      "lat": 36.126904,
      "lng": -86.788732,
      "rentSummary": "$1,320+/mo",
      "name": "12 South Flats"
    },
    {
      "lat": 36.149200,
      "lng": -86.795541,
      "rentSummary": "$1,473+/mo",
      "name": "The Morris"
    },
    {
      "lat": 36.128921,
      "lng": -86.777911,
      "rentSummary": "$1,380+/mo",
      "name": "Melrose Apartments"
    },
    {
      "lat": 36.136897,
      "lng": -86.797871,
      "rentSummary": "$1,600+/mo",
      "name": "1810 Belcourt Apartments"
    },
    {
      "lat": 36.140900,
      "lng": -86.834300,
      "rentSummary": "$1,049+/mo",
      "name": "Station 40"
    },
    {
      "lat": 36.104137,
      "lng": -86.813998,
      "rentSummary": "$1,799+/mo",
      "name": "Vertis Green Hills"
    },
    {
      "lat": 36.176858,
      "lng": -86.755940,
      "rentSummary": "$1,285+/mo",
      "name": "Amplify on Main"
    },
    {
      "lat": 36.179497,
      "lng": -86.791678,
      "rentSummary": "$1,236+/mo",
      "name": "The Flats at Taylor Place"
    },
    {
      "lat": 36.139250,
      "lng": -86.797709,
      "rentSummary": "$1,565+/mo",
      "name": "The Village at Vanderbilt"
    },
    {
      "lat": 36.162362,
      "lng": -86.780998,
      "rentSummary": "$1,307+/mo",
      "name": "The Cumberland"
    },
    {
      "lat": 36.152250,
      "lng": -86.841900,
      "rentSummary": "$1,065+/mo",
      "name": "West 46th Apartments"
    },
    {
      "lat": 36.135781,
      "lng": -86.801144,
      "rentSummary": "$1,350+/mo",
      "name": "2100 Acklen Flats"
    },
    {
      "lat": 36.147229,
      "lng": -86.815605,
      "rentSummary": "$1,250+/mo",
      "name": "Duet"
    },
    {
      "lat": 36.156422,
      "lng": -86.810060,
      "rentSummary": "$1,301+/mo",
      "name": "Charlotte at Midtown"
    },
    {
      "lat": 36.175901,
      "lng": -86.784639,
      "rentSummary": "$1,394+/mo",
      "name": "Broadstone Germantown"
    },
    {
      "lat": 36.128598,
      "lng": -86.777706,
      "rentSummary": "$1,340+/mo",
      "name": "23Hundred at Berry Hill"
    },
    {
      "lat": 36.117684,
      "lng": -86.775827,
      "rentSummary": "$1,277+/mo",
      "name": "Gale Lofts"
    },
    {
      "lat": 36.174128,
      "lng": -86.763805,
      "rentSummary": "$1,420+/mo",
      "name": "Stacks on Main"
    },
    {
      "lat": 36.141265,
      "lng": -86.747621,
      "rentSummary": "$1,169+/mo",
      "name": "The Flats at Walden Grove"
    },
    {
      "lat": 36.162978,
      "lng": -86.780282,
      "rentSummary": "$1,650+/mo",
      "name": "505 Nashville"
    },
    {
      "lat": 36.154759,
      "lng": -86.798818,
      "rentSummary": "$1,350+/mo",
      "name": "1818 Church Apartments"
    },
    {
      "lat": 36.134821,
      "lng": -86.776859,
      "rentSummary": "$1,185+/mo",
      "name": "Parkview Midtown Apartments"
    },
    {
      "lat": 36.152385,
      "lng": -86.803453,
      "rentSummary": "$1,480+/mo",
      "name": "The Dallas on Elliston"
    },
    {
      "lat": 36.134325,
      "lng": -86.788535,
      "rentSummary": "$1,350+/mo",
      "name": "The Chelsea"
    },
    {
      "lat": 36.152911,
      "lng": -86.804826,
      "rentSummary": "$1,350+/mo",
      "name": "Edge Midtown"
    },
    {
      "lat": 36.131717,
      "lng": -86.820407,
      "rentSummary": "$1,400+/mo",
      "name": "The Grove at Whitworth"
    },
    {
      "lat": 36.152607,
      "lng": -86.782037,
      "rentSummary": "$1,199+/mo",
      "name": "Pine Street Flats"
    }
  ]
}